sanic_jinja2_spf/__init__.py
sanic_jinja2_spf/plugin.py
Sanic_Jinja2_SPF-0.8.0.dist-info/LICENSE
Sanic_Jinja2_SPF-0.8.0.dist-info/METADATA
Sanic_Jinja2_SPF-0.8.0.dist-info/WHEEL
Sanic_Jinja2_SPF-0.8.0.dist-info/top_level.txt
Sanic_Jinja2_SPF-0.8.0.dist-info/RECORD
