Metadata-Version: 2.1
Name: Sanic-Jinja2-SPF
Version: 0.8.0
Summary: A SPF compatible distribution of Sanic-Jinja2. Wraps upstream Sanic-Jinja2.
Home-page: https://github.com/ashleysommer/sanic-jinja2-spf
Author: Ashley Sommer, Lix Xu
Author-email: ashleysommer@gmail.com
License: MIT
Platform: any
Classifier: Environment :: Web Environment
Classifier: Intended Audience :: Developers
Classifier: License :: OSI Approved :: MIT License
Classifier: Operating System :: OS Independent
Classifier: Programming Language :: Python
Classifier: Programming Language :: Python :: 3
Classifier: Programming Language :: Python :: 3 :: Only
Classifier: Programming Language :: Python :: Implementation :: CPython
Classifier: Programming Language :: Python :: Implementation :: PyPy
Classifier: Topic :: Internet :: WWW/HTTP :: Dynamic Content
Classifier: Topic :: Software Development :: Libraries :: Python Modules
Requires-Dist: sanic (>=18.12)
Requires-Dist: sanic-plugins-framework (>=0.9.0)
Requires-Dist: sanic-jinja2 (>=0.8.0)
